docs/__init__.py
docs/conf.py
docs/examples/__init__.py
docs/examples/services.py
test/__init__.py
test/conftest.py
test/integration/__init__.py
test/integration/test_app_runner.py
test/integration/test_authentication.py
test/integration/test_clients.py
test/integration/test_exception_handling.py
test/integration/test_message_handler.py
test/integration/test_really_long_strings.py
test/integration/test_unicode.py
test/unit/__init__.py
test/unit/test_authentication.py
test/unit/test_backends.py
test/unit/test_configure.py
wampy/__init__.py
wampy/auth.py
wampy/constants.py
wampy/errors.py
wampy/interfaces.py
wampy/message_handler.py
wampy/mixins.py
wampy/serializers.py
wampy/session.py
wampy/backends/__init__.py
wampy/backends/errors.py
wampy/backends/eventlet_.py
wampy/backends/gevent_.py
wampy/cli/__init__.py
wampy/cli/main.py
wampy/cli/run.py
wampy/config/__init__.py
wampy/config/defaults.py
wampy/messages/__init__.py
wampy/messages/abort.py
wampy/messages/authenticate.py
wampy/messages/base.py
wampy/messages/call.py
wampy/messages/cancel.py
wampy/messages/challenge.py
wampy/messages/error.py
wampy/messages/event.py
wampy/messages/goodbye.py
wampy/messages/hello.py
wampy/messages/invocation.py
wampy/messages/publish.py
wampy/messages/register.py
wampy/messages/registered.py
wampy/messages/result.py
wampy/messages/subscribe.py
wampy/messages/subscribed.py
wampy/messages/welcome.py
wampy/messages/yield_.py
wampy/peers/__init__.py
wampy/peers/clients.py
wampy/peers/routers.py
wampy/roles/__init__.py
wampy/roles/callee.py
wampy/roles/caller.py
wampy/roles/publisher.py
wampy/roles/subscriber.py
wampy/testing/__init__.py
wampy/testing/helpers.py
wampy/testing/pytest_plugin.py
wampy/transports/__init__.py
wampy/transports/websocket/__init__.py
wampy/transports/websocket/connection.py
wampy/transports/websocket/frames.py
wampy-1.1.0.dist-info/LICENSE
wampy-1.1.0.dist-info/METADATA
wampy-1.1.0.dist-info/WHEEL
wampy-1.1.0.dist-info/entry_points.txt
wampy-1.1.0.dist-info/top_level.txt
wampy-1.1.0.dist-info/RECORD
