Metadata-Version: 2.1
Name: wampy
Version: 1.1.0
Summary: WAMP RPC and Pub/Sub for python interactive shells, scripts, apps and microservices
Home-page: https://github.com/noisyboiler/wampy
Author: Simon Harrison
Author-email: noisyboiler@googlemail.com
License: Mozilla Public License 2.0
Keywords: WAMP RPC
Platform: UNKNOWN
Classifier: Development Status :: 4 - Beta
Classifier: License :: OSI Approved :: Mozilla Public License 2.0 (MPL 2.0)
Classifier: Programming Language :: Python :: 3.7
Classifier: Programming Language :: Python :: 3.8
Classifier: Programming Language :: Python :: 3.9
Requires-Dist: attrs (==20.3.0)
Requires-Dist: eventlet (>=0.24.1)
Requires-Dist: six (==1.13.0)
Requires-Dist: simplejson (>=3.11.1)
Requires-Dist: gevent (>=21.1.2)
Provides-Extra: dev
Requires-Dist: colorlog (>=3.1.4) ; extra == 'dev'
Requires-Dist: coverage (>=3.7.1) ; extra == 'dev'
Requires-Dist: crossbar (==21.3.1) ; extra == 'dev'
Requires-Dist: flake8 (>=3.5.0) ; extra == 'dev'
Requires-Dist: gevent-websocket (>=0.10.1) ; extra == 'dev'
Requires-Dist: pytest (>=4.0.2) ; extra == 'dev'
Requires-Dist: mock (>=1.3.0) ; extra == 'dev'
Provides-Extra: docs
Requires-Dist: Sphinx (==1.4.5) ; extra == 'docs'
Requires-Dist: guzzle-sphinx-theme ; extra == 'docs'
